grape/__init__.py
grape/fault_diagnosis.py
grape/general_graph.py
grape/meta.py
grape/parallel_general_graph.py
grape/utils.py
tests/__init__.py
tests/general_graph.py
tests/test_fault_diagnosis.py
tests/test_input_graph.py
tests/test_integer_graph.py
tests/test_parallel_integer_graph.py
tests/test_shortest_path.py
grape_mathlab-2.0.0.dist-info/LICENSE
grape_mathlab-2.0.0.dist-info/METADATA
grape_mathlab-2.0.0.dist-info/WHEEL
grape_mathlab-2.0.0.dist-info/top_level.txt
grape_mathlab-2.0.0.dist-info/RECORD
