Metadata-Version: 2.1
Name: grape-mathlab
Version: 2.0.0
Summary: GRAph Parallel Environment.
Home-page: https://github.com/mathLab/GRAPE
Author: Aurora Maurizio, Martina Teruzzi, Nicola Demo
Author-email: auroramaurizio1@gmail.com, teruzzi.martina@gmail.com, demo.nicola@gmail.com
License: MIT
Keywords: risk-analysis graph-theory parallel-programming shortest-path system-analysis fault-diagnostics
Classifier: Development Status :: 5 - Production/Stable
Classifier: License :: OSI Approved :: MIT License
Classifier: Programming Language :: Python :: 3.6
Classifier: Intended Audience :: Science/Research
Classifier: Topic :: Scientific/Engineering :: Mathematics
License-File: LICENSE
Requires-Dist: networkx
Requires-Dist: numpy
Requires-Dist: scipy
Requires-Dist: matplotlib
Requires-Dist: pandas
Requires-Dist: deap
Provides-Extra: docs
Requires-Dist: sphinx ; extra == 'docs'
Requires-Dist: sphinx-rtd-theme ; extra == 'docs'
Provides-Extra: test
Requires-Dist: pytest ; extra == 'test'
Requires-Dist: pytest-cov ; extra == 'test'
